alpacalert_cmd/__init__.py
alpacalert_cmd/__main__.py
alpacalert_cmd/console_grafana.py
alpacalert_cmd/console_kubernetes.py
alpacalert_cmd/console_prometheus.py
alpacalert_cmd-0.1.0.dist-info/METADATA
alpacalert_cmd-0.1.0.dist-info/WHEEL
alpacalert_cmd-0.1.0.dist-info/entry_points.txt
alpacalert_cmd-0.1.0.dist-info/top_level.txt
alpacalert_cmd-0.1.0.dist-info/RECORD
